grokcore.json-4.1-py3.8-nspkg.pth
grokcore/json/__init__.py
grokcore/json/components.py
grokcore/json/configure.zcml
grokcore/json/ftesting.zcml
grokcore/json/interfaces.py
grokcore/json/meta.py
grokcore/json/meta.zcml
grokcore/json/testing.py
grokcore/json/tests/__init__.py
grokcore/json/tests/test_base.py
grokcore/json/tests/test_functional.py
grokcore/json/tests/base/__init__.py
grokcore/json/tests/base/json/__init__.py
grokcore/json/tests/base/json/json_layers.py
grokcore/json/tests/base/json/missing_permission.py
grokcore/json/tests/base/json/missing_permission2.py
grokcore/json/tests/base/json/missing_permission3.py
grokcore/json/tests/base/json/multiple_require.py
grokcore/json/tests/base/json/nocontext.py
grokcore/json/tests/base/json/nomethods.py
grokcore/json/tests/base/json/view_lookup.py
grokcore/json/tests/functional/__init__.py
grokcore/json/tests/functional/json/__init__.py
grokcore/json/tests/functional/json/json.py
grokcore.json-4.1.dist-info/LICENSE.txt
grokcore.json-4.1.dist-info/METADATA
grokcore.json-4.1.dist-info/WHEEL
grokcore.json-4.1.dist-info/namespace_packages.txt
grokcore.json-4.1.dist-info/top_level.txt
grokcore.json-4.1.dist-info/RECORD
